dsloader/__init__.py
dsloader/constants.py
dsloader/exceptions.py
dsloader/py.typed
dsloader/utils.py
dsloader/case/__init__.py
dsloader/case/aws.py
dsloader/case/hpc.py
dsloader/case/smartds.py
dsloader/cli/__init__.py
dsloader/cli/cli.py
dsloader/cli/download_case.py
dsloader-0.0.1.dist-info/METADATA
dsloader-0.0.1.dist-info/WHEEL
dsloader-0.0.1.dist-info/RECORD
